nomad_camels_driver_thorlabs_ddr_25/thorlabs_ddr_25.py
nomad_camels_driver_thorlabs_ddr_25/thorlabs_ddr_25_ophyd.py
nomad_camels_driver_thorlabs_ddr_25-0.0.2.dist-info/LICENSE.txt
nomad_camels_driver_thorlabs_ddr_25-0.0.2.dist-info/METADATA
nomad_camels_driver_thorlabs_ddr_25-0.0.2.dist-info/WHEEL
nomad_camels_driver_thorlabs_ddr_25-0.0.2.dist-info/top_level.txt
nomad_camels_driver_thorlabs_ddr_25-0.0.2.dist-info/RECORD
