Metadata-Version: 2.1
Name: nomad-camels-driver-thorlabs-ddr-25
Version: 0.0.2
Summary: Basic instrument driver for the Thorlabs rotation stage DDR 25.
Author-email: Simon Sochiera <s.sochiera@web.de>
Project-URL: GitHub Page, https://github.com/FAU-LAP/CAMELS_drivers
Project-URL: Documentation, https://fau-lap.github.io/NOMAD-CAMELS
Requires-Python: >=3.11.3
License-File: LICENSE.txt
Requires-Dist: pylablib
